django_rest_framework_multi_slug_field-0.2.0.dist-info/DESCRIPTION.rst
django_rest_framework_multi_slug_field-0.2.0.dist-info/METADATA
django_rest_framework_multi_slug_field-0.2.0.dist-info/metadata.json
django_rest_framework_multi_slug_field-0.2.0.dist-info/RECORD
django_rest_framework_multi_slug_field-0.2.0.dist-info/top_level.txt
django_rest_framework_multi_slug_field-0.2.0.dist-info/WHEEL
rest_framework_msf/__init__.py
rest_framework_msf/fields.py
rest_framework_msf/models.py
