Metadata-Version: 2.0
Name: django-rest-framework-multi-slug-field
Version: 0.2.0
Summary: A field for representing a relationship via multiple fields on the target
Home-page: https://github.com/simpleenergy/django-rest-framework-multi-slug-field
Author: Piper Merriam
Author-email: piper@simpleenergy.com
License: BSD
Keywords: django-rest-framework-multi-slug-field
Platform: UNKNOWN
Classifier: Development Status :: 2 - Pre-Alpha
Classifier: Framework :: Django
Classifier: Intended Audience :: Developers
Classifier: License :: OSI Approved :: BSD License
Classifier: Natural Language :: English
Classifier: Programming Language :: Python :: 2
Classifier: Programming Language :: Python :: 2.6
Classifier: Programming Language :: Python :: 2.7
Classifier: Programming Language :: Python :: 3
Classifier: Programming Language :: Python :: 3.3
Requires-Dist: djangorestframework (>=2.3.14)
